{
    "@class": "com.kony.gen.viz.model.component.KVizImage2",
    "DNDConfig": null,
    "__parentReadjusting__": false,
    "_base64_": null,
    "_height_": {
        "type": "string",
        "value": "100%"
    },
    "_left_": {
        "type": "string",
        "value": "0"
    },
    "_margin_": [
        0,
        0,
        0,
        0
    ],
    "_padding_": [
        0,
        0,
        0,
        0
    ],
    "_skin_": "seb56d7dd9334fb2a03ebc3eefa9b428",
    "_src_": "imagedrag.png",
    "_top_": {
        "type": "string",
        "value": "0"
    },
    "_width_": {
        "type": "string",
        "value": "100%"
    },
    "canUpdateUI": true,
    "containerweight": 100,
    "context": {
        "channel": "mobile",
        "formID": "frmViewCar",
        "platform": "android",
        "templateType": "forms",
        "topLevelBox": null
    },
    "id": "carImage",
    "imagescalemode": 1,
    "info": null,
    "iscustomlayout": false,
    "isvisible": true,
    "kuid": "a6c0c173bfb747c1bebea0685b6b93c9",
    "name": "kony.ui.Image2",
    "parent": "imageContainer",
    "pf": "frmViewCar",
    "retaincontentalignment": false,
    "retainflexpositionproperties": false,
    "srcType": 1,
    "wType": "Image",
    "widgetalignment": 5
}